humannum-1.2.1.dist-info/METADATA
humannum-1.2.1.dist-info/WHEEL
humannum-1.2.1.dist-info/entry_points.txt
humannum-1.2.1.dist-info/licenses/LICENSE
humannum/__init__.py
humannum/baseint.py
humannum/binary.py
humannum/bytesize.py
humannum/converter.py
humannum/freq.py
humannum/hex.py
humannum-1.2.1.dist-info/RECORD
