Metadata-Version: 2.1
Name: humannum
Version: 1.2.1
Summary: Human Friendly Numbers
Classifier: Programming Language :: Python :: 3
Classifier: Operating System :: OS Independent
Project-URL: Homepage, https://github.com/nbiotcloud/humannum
Project-URL: Documentation, https://humannum.readthedocs.io/en/stable/
Project-URL: Bug Tracker, https://github.com/nbiotcloud/humannum/issues
Requires-Python: <4.0,>=3.10.0
Requires-Dist: humanfriendly>=10.0
